{
  "id": "46c4fea3-6ead-465f-841b-0bcbaed1501a",
  "title": "Dhruvathaare",
  "slug": "dhruvathaare",
  "thumbnail_url": "https://image.tmdb.org/t/p/w500/aJMC7vzvfE4ttvfLTR5haXwwl93.jpg",
  "is_premium": false,
  "country": "India",
  "language": "en",
  "release_year": 2025,
  "duration": null,
  "rating": null,
  "description": "Parivartan, a heartbroken young man, struggles to heal from a painful breakup, while Apoorva tries to move forward from her past relationship. Their lives intersect on social media, sparking a beautiful romance. However, their newfound love soon faces an unexpected and formidable challenge.",
  "created_at": "2026-07-09T17:04:52.971Z",
  "genres": [],
  "_index": 738,
  "stream_url_1080p": "https://movie.ctgfun.com/disk4/South%20Indian%20Movies/Dhruvathaare%20(2024)%20Kannada%201080p%20WEBRip%20x264%20ESub%20%5BDDN%5D/Dhruvathaare%20(2024)%20Kannada%201080p%20WEBRip%20x264%20ESub%20%5bDDN%5d.mkv",
  "stream_url_720p": null,
  "stream_url_480p": null
}