{
  "id": "4703859f-ba9a-46bd-8f7c-b719a6c4e523",
  "title": "Saudi Vellakka",
  "slug": "saudi-vellakka",
  "thumbnail_url": "https://image.tmdb.org/t/p/w500/8weODzUVpgcjS3QeFkNRqzg37Bt.jpg",
  "is_premium": false,
  "country": "India",
  "language": "Malayalam",
  "release_year": 2022,
  "duration": 146,
  "rating": 7.5,
  "description": "Abhilash Sasidharan receives a summons warrant to appear in court for a case from his childhood. Desperate to learn the truth, he finds a small conflict snowballed into a larger one that changed the lives of everyone involved",
  "created_at": "2026-07-09T17:47:12.253Z",
  "genres": [
    {
      "name": "Drama",
      "slug": "drama"
    }
  ],
  "_index": 2774,
  "stream_url_1080p": "https://movie.ctgfun.com/disk4/South%20Indian%20Movies/Saudi%20Vellakka%20(2022)%20Malayalam%20HQ%20PreDVD%20-1080p%20-%20x264%20%5BDDN%5D/Saudi%20Vellakka%20(2022)%20Malayalam%20HQ%20PreDVD%20-1080p%20-%20x264%20%5bDDN%5d.mkv",
  "stream_url_720p": null,
  "stream_url_480p": null
}