{
  "id": "8d922610-6faf-4835-8e8d-2d1a34720c38",
  "title": "Laughing Buddha",
  "slug": "laughing-buddha",
  "thumbnail_url": "https://image.tmdb.org/t/p/w500/mhF9LSMqr5fHqfU5i9J4VJsSTOB.jpg",
  "is_premium": false,
  "country": "India",
  "language": "Kannada",
  "release_year": 2024,
  "duration": 131,
  "rating": 5.5,
  "description": "Explores the life and personal struggles of a police head constable.",
  "created_at": "2026-07-09T17:11:12.851Z",
  "genres": [
    {
      "name": "Comedy",
      "slug": "comedy"
    },
    {
      "name": "Drama",
      "slug": "drama"
    }
  ],
  "_index": 1069,
  "stream_url_1080p": "https://movie.ctgfun.com/disk4/South%20Indian%20Movies/Laughing%20Buddha%20(2024)%20Kannada%201080p%20WEBRip%20x264%20ESub%20%5BDDN%5D/Laughing%20Buddha%20(2024)%20Kannada%201080p%20WEBRip%20x264%20ESub%20%5bDDN%5d.mkv",
  "stream_url_720p": null,
  "stream_url_480p": null
}