{
  "id": "cbbd2d32-6943-4de9-a75b-f98a1d63af98",
  "title": "The Naked Gun",
  "slug": "the-naked-gun",
  "thumbnail_url": "https://image.tmdb.org/t/p/w500/rwla9vqzrKVVKVKiOuROTIXGsxj.jpg",
  "is_premium": false,
  "country": "United States",
  "language": "Hungarian",
  "release_year": 2025,
  "duration": 85,
  "rating": 6.366,
  "description": "Only one man has the particular set of skills... to lead Police Squad and save the world: Lt. Frank Drebin Jr. Following in his father's footsteps, he must solve a murder case to prevent Police Squad from closure.",
  "created_at": "2026-07-09T16:53:23.227Z",
  "genres": [
    {
      "name": "Action",
      "slug": "action"
    },
    {
      "name": "Comedy",
      "slug": "comedy"
    },
    {
      "name": "Crime",
      "slug": "crime"
    }
  ],
  "_index": 707,
  "stream_url_1080p": "https://ftp.ctgfun.com/English/The.Naked.Gun.2025.1080p.WEBRip.x264%20%5BDDN%5D/The.Naked.Gun.2025.1080p.WEBRip.x264%20%5BDDN%5D.mp4",
  "stream_url_720p": null,
  "stream_url_480p": null
}