{
  "id": "d9a50f13-25df-47e2-bfd6-69a0567fec10",
  "title": "Month of Madhu",
  "slug": "month-of-madhu",
  "thumbnail_url": "https://image.tmdb.org/t/p/w500/u4TzYGDWZecR69x139wfRUxjDUr.jpg",
  "is_premium": false,
  "country": "India",
  "language": "Telugu",
  "release_year": 2023,
  "duration": 140,
  "rating": 6.3,
  "description": "Madhumati, a 19-year-old Indo-American girl, whose visit to Vizag for a family wedding takes an unforeseen turn after a clash with her mother. Meanwhile, Madhusudhan, a separated and unemployed man, grapples with his failing marriage to Lekha. Their paths cross one evening, setting the stage for profound explorations of relationships and self.",
  "created_at": "2026-07-09T17:31:33.558Z",
  "genres": [
    {
      "name": "Drama",
      "slug": "drama"
    },
    {
      "name": "Romance",
      "slug": "romance"
    }
  ],
  "_index": 2193,
  "stream_url_1080p": "https://movie.ctgfun.com/disk4/South%20Indian%20Movies/Month%20Of%20Madhu%20(2023)%20Telugu%201080p%20WEBRip%20x264%20ESub%20%5BDDN%5D/Month%20Of%20Madhu%20(2023)%20Telugu%201080p%20WEBRip%20x264%20ESub%20%5bDDN%5d.mkv",
  "stream_url_720p": null,
  "stream_url_480p": null
}